Workbook

Sheet Sales_Data
A1: Order ID | B1: Order Date | C1: Region | D1: Category | E1: Product | F1: Customer | G1: Quantity | H1: Unit Price | I1: Sales | J1: Cost | K1: Profit
A2: ORD0001 | B2: 45985 | C2: North | D2: Electronics | E2: Keyboard | F2: Customer 8 | G2: 4 | H2: 2500 | I2: 10000 | J2: 6390.71 | K2: 3609.29
A3: ORD0002 | B3: 45710 | C3: North | D3: Office Supplies | E3: Stapler | F3: Customer 2 | G3: 1 | H3: 300 | I3: 300 | J3: 187.87 | K3: 112.13
A4: ORD0003 | B4: 45777 | C4: North | D4: Office Supplies | E4: Notebook | F4: Customer 18 | G4: 7 | H4: 180 | I4: 1260 | J4: 833.77 | K4: 426.23
A5: ORD0004 | B5: 45959 | C5: East | D5: Electronics | E5: Monitor | F5: Customer 14 | G5: 6 | H5: 18000 | I5: 108000 | J5: 73202.83 | K5: 34797.17
A6: ORD0005 | B6: 45768 | C6: East | D6: Electronics | E6: Laptop | F6: Customer 13 | G6: 2 | H6: 65000 | I6: 130000 | J6: 91066.85 | K6: 38933.15
A7: ORD0006 | B7: 45834 | C7: East | D7: Electronics | E7: Mouse | F7: Customer 18 | G7: 2 | H7: 1200 | I7: 2400 | J7: 2093.93 | K7: 306.07
A8: ORD0007 | B8: 45851 | C8: North | D8: Office Supplies | E8: Pen Set | F8: Customer 20 | G8: 6 | H8: 250 | I8: 1500 | J8: 1142.49 | K8: 357.51
A9: ORD0008 | B9: 46018 | C9: North | D9: Electronics | E9: Monitor | F9: Customer 10 | G9: 2 | H9: 18000 | I9: 36000 | J9: 30221.6 | K9: 5778.4
A10: ORD0009 | B10: 45709 | C10: West | D10: Furniture | E10: Table | F10: Customer 12 | G10: 3 | H10: 9000 | I10: 27000 | J10: 18998.57 | K10: 8001.43
A11: ORD0010 | B11: 45765 | C11: East | D11: Office Supplies | E11: Printer Paper | F11: Customer 20 | G11: 3 | H11: 450 | I11: 1350 | J11: 1011.9 | K11: 338.1
A12: ORD0011 | B12: 45783 | C12: South | D12: Furniture | E12: Table | F12: Customer 9 | G12: 9 | H12: 9000 | I12: 81000 | J12: 53580.87 | K12: 27419.13
A13: ORD0012 | B13: 45824 | C13: North | D13: Electronics | E13: Laptop | F13: Customer 11 | G13: 7 | H13: 65000 | I13: 455000 | J13: 307110.19 | K13: 147889.81
... A101: ORD0100 | B101: 45666 | C101: North | D101: Furniture | E101: Desk | F101: Customer 13 | G101: 4 | H101: 12000 | I101: 48000 | J101: 32915.41 | K101: 15084.59

Sheet Analysis
A1: SALES DATA ANALYSIS
A3: KPI | B3: Value
A4: Total Sales | B4: =SUM(Sales_Data!I2:I101) -> 6287000
A5: Total Cost | B5: =SUM(Sales_Data!J2:J101) -> 4636263.8
A6: Total Profit | B6: =SUM(Sales_Data!K2:K101) -> 1650736.2
A7: Total Orders | B7: =COUNTA(Sales_Data!A2:A101) -> 100
A8: Total Quantity | B8: =SUM(Sales_Data!G2:G101) -> 500
A9: Average Order Value | B9: =B4/B7 -> 62870
A12: Region | B12: Sales | C12: Profit | E12: Category | F12: Sales | G12: Profit
A13: North | B13: =SUMIF(Sales_Data!C2:C101,A13,Sales_Data!I2:I101) -> 1793440 | C13: =SUMIF(Sales_Data!C2:C101,A13,Sales_Data!K2:K101) -> 516114.02 | E13: Electronics | F13: =SUMIF(Sales_Data!D2:D101,E13,Sales_Data!I2:I101) -> 4590900 | G13: =SUMIF(Sales_Data!D2:D101,E13,Sales_Data!K2:K101) -> 1230508.4
A14: South | B14: =SUMIF(Sales_Data!C2:C101,A14,Sales_Data!I2:I101) -> 1278060 | C14: =SUMIF(Sales_Data!C2:C101,A14,Sales_Data!K2:K101) -> 330967.98 | E14: Furniture | F14: =SUMIF(Sales_Data!D2:D101,E14,Sales_Data!I2:I101) -> 1661500 | G14: =SUMIF(Sales_Data!D2:D101,E14,Sales_Data!K2:K101) -> 412003.86
A15: East | B15: =SUMIF(Sales_Data!C2:C101,A15,Sales_Data!I2:I101) -> 2052530 | C15: =SUMIF(Sales_Data!C2:C101,A15,Sales_Data!K2:K101) -> 482676.45 | E15: Office Supplies | F15: =SUMIF(Sales_Data!D2:D101,E15,Sales_Data!I2:I101) -> 34600 | G15: =SUMIF(Sales_Data!D2:D101,E15,Sales_Data!K2:K101) -> 8223.91
A16: West | B16: =SUMIF(Sales_Data!C2:C101,A16,Sales_Data!I2:I101) -> 1162970 | C16: =SUMIF(Sales_Data!C2:C101,A16,Sales_Data!K2:K101) -> 320977.72
A20: Product | B20: Sales | E20: Month | F20: Sales
A21: Laptop | B21: =SUMIF(Sales_Data!E2:E101,A21,Sales_Data!I2:I101) -> 2990000 | E21: 45658 | F21: =SUMIFS(Sales_Data!I2:I101,Sales_Data!B2:B101,">="&E21,Sales_Data!B2:B101,"<"&EDATE(E21,1)) -> 589700
A22: Monitor | B22: =SUMIF(Sales_Data!E2:E101,A22,Sales_Data!I2:I101) -> 1512000 | E22: 45689 | F22: =SUMIFS(Sales_Data!I2:I101,Sales_Data!B2:B101,">="&E22,Sales_Data!B2:B101,"<"&EDATE(E22,1)) -> 475610
A23: Keyboard | B23: =SUMIF(Sales_Data!E2:E101,A23,Sales_Data!I2:I101) -> 32500 | E23: 45717 | F23: =SUMIFS(Sales_Data!I2:I101,Sales_Data!B2:B101,">="&E23,Sales_Data!B2:B101,"<"&EDATE(E23,1)) -> 38850
A24: Mouse | B24: =SUMIF(Sales_Data!E2:E101,A24,Sales_Data!I2:I101) -> 56400 | E24: 45748 | F24: =SUMIFS(Sales_Data!I2:I101,Sales_Data!B2:B101,">="&E24,Sales_Data!B2:B101,"<"&EDATE(E24,1)) -> 402210
A25: Office Chair | B25: =SUMIF(Sales_Data!E2:E101,A25,Sales_Data!I2:I101) -> 459000 | E25: 45778 | F25: =SUMIFS(Sales_Data!I2:I101,Sales_Data!B2:B101,">="&E25,Sales_Data!B2:B101,"<"&EDATE(E25,1)) -> 822950
A26: Desk | B26: =SUMIF(Sales_Data!E2:E101,A26,Sales_Data!I2:I101) -> 564000 | E26: 45809 | F26: =SUMIFS(Sales_Data!I2:I101,Sales_Data!B2:B101,">="&E26,Sales_Data!B2:B101,"<"&EDATE(E26,1)) -> 947190
A27: Bookshelf | B27: =SUMIF(Sales_Data!E2:E101,A27,Sales_Data!I2:I101) -> 188500 | E27: 45839 | F27: =SUMIFS(Sales_Data!I2:I101,Sales_Data!B2:B101,">="&E27,Sales_Data!B2:B101,"<"&EDATE(E27,1)) -> 1242540
A28: Table | B28: =SUMIF(Sales_Data!E2:E101,A28,Sales_Data!I2:I101) -> 450000 | E28: 45870 | F28: =SUMIFS(Sales_Data!I2:I101,Sales_Data!B2:B101,">="&E28,Sales_Data!B2:B101,"<"&EDATE(E28,1)) -> 600800
A29: Printer Paper | B29: =SUMIF(Sales_Data!E2:E101,A29,Sales_Data!I2:I101) -> 7650 | E29: 45901 | F29: =SUMIFS(Sales_Data!I2:I101,Sales_Data!B2:B101,">="&E29,Sales_Data!B2:B101,"<"&EDATE(E29,1)) -> 292100
A30: Notebook | B30: =SUMIF(Sales_Data!E2:E101,A30,Sales_Data!I2:I101) -> 7200 | E30: 45931 | F30: =SUMIFS(Sales_Data!I2:I101,Sales_Data!B2:B101,">="&E30,Sales_Data!B2:B101,"<"&EDATE(E30,1)) -> 552360
A31: Pen Set | B31: =SUMIF(Sales_Data!E2:E101,A31,Sales_Data!I2:I101) -> 10750 | E31: 45962 | F31: =SUMIFS(Sales_Data!I2:I101,Sales_Data!B2:B101,">="&E31,Sales_Data!B2:B101,"<"&EDATE(E31,1)) -> 235940
A32: Stapler | B32: =SUMIF(Sales_Data!E2:E101,A32,Sales_Data!I2:I101) -> 9000 | E32: 45992 | F32: =SUMIFS(Sales_Data!I2:I101,Sales_Data!B2:B101,">="&E32,Sales_Data!B2:B101,"<"&EDATE(E32,1)) -> 86750

Sheet Project_Overview
A1: Project | B1: Sales Data Analysis
A2: Objective | B2: Analyze sales performance, profitability, regions, products and monthly trends.
A3: Tools | B3: Microsoft Excel, Pivot-style analysis, formulas and charts
A4: Dataset | B4: 100 sample sales transactions for 2025
A5: Key Skills | B5: Data cleaning, KPI analysis, SUMIF/SUMIFS, business reporting and visualization
A6: Key Questions | B6: Which region performs best? Which categories/products generate the most sales? How does sales change by month?
A7: Author | B7: GK Vamsi - SQL Developer | Reporting Analyst | Data Analyst
